spriteutils/__init__.py
spriteutils/spriteutil.py
spriteutils-1.0.2.dist-info/METADATA
spriteutils-1.0.2.dist-info/WHEEL
spriteutils-1.0.2.dist-info/top_level.txt
spriteutils-1.0.2.dist-info/RECORD
